newPassword/__init__.py
newPassword/passwordGenerator.py
newPassword-2.1.1.1.dist-info/LICENSE.txt
newPassword-2.1.1.1.dist-info/METADATA
newPassword-2.1.1.1.dist-info/WHEEL
newPassword-2.1.1.1.dist-info/top_level.txt
newPassword-2.1.1.1.dist-info/RECORD
