Metadata-Version: 2.1
Name: newPassword
Version: 2.1.1.1
Summary: Password generator package
Author: Nipun Dogra
Classifier: Programming Language :: Python :: 3
Classifier: License :: OSI Approved :: MIT License
Classifier: Operating System :: OS Independent
Requires-Python: >=3.6
License-File: LICENSE.txt
